ensure_shebang_runtime/__init__.py
ensure_shebang_runtime-0.4.0.dist-info/licenses/LICENSE
ensure_shebang_runtime-0.4.0.dist-info/METADATA
ensure_shebang_runtime-0.4.0.dist-info/WHEEL
ensure_shebang_runtime-0.4.0.dist-info/top_level.txt
ensure_shebang_runtime-0.4.0.dist-info/RECORD
