Metadata-Version: 2.4
Name: ensure-shebang-runtime
Version: 0.4.0
Summary: Re-executes Python scripts under the interpreter specified in the shebang line.
Author-email: simranjeet <simranjeetdua@gmail.com>
License: MIT
Requires-Python: >=3.6
License-File: LICENSE
Dynamic: license-file
